README.rst
setup.py
bin/msd
msd/__init__.py
msd/brand.py
msd/campaign.py
msd/category.py
msd/category_data.py
msd/claim.py
msd/cmd.py
msd/company.py
msd/company_data.py
msd/db.py
msd/merge.py
msd/norm.py
msd/output.py
msd/rating.py
msd/scraper.py
msd/scratch.py
msd/table.py
msd/target.py
msd/url.py
msd.egg-info/PKG-INFO
msd.egg-info/SOURCES.txt
msd.egg-info/dependency_links.txt
msd.egg-info/requires.txt
msd.egg-info/top_level.txt