Metadata-Version: 1.1
Name: msd
Version: 0.1.3
Summary: Merge SpendRight scraper data
Home-page: http://github.com/spendright/msd
Author: David Marin
Author-email: dave@spendright.org
License: Apache
Platform: UNKNOWN
Classifier: Development Status :: 3 - Alpha
Classifier: License :: OSI Approved :: Apache Software License
Classifier: Natural Language :: English
Classifier: Operating System :: OS Independent
Classifier: Programming Language :: Python
Classifier: Programming Language :: Python :: 3
Classifier: Programming Language :: Python :: 3.3
Classifier: Programming Language :: Python :: 3.4
Classifier: Programming Language :: Python :: 3.5
Provides: msd
